MANIFEST.in
setup.py
hnph_utils/__init__.py
hnph_utils/date_util.py
hnph_utils/encryption_util.py
hnph_utils/excel_util.py
hnph_utils/file_util.py
hnph_utils/image_util.py
hnph_utils/path_util.py
hnph_utils/pdf_util.py
hnph_utils/qrcode_util.py
hnph_utils/redis_util.py
hnph_utils/sms_util.py
hnph_utils/string_util.py
hnph_utils/zip_util.py
hnph_utils.egg-info/PKG-INFO
hnph_utils.egg-info/SOURCES.txt
hnph_utils.egg-info/dependency_links.txt
hnph_utils.egg-info/not-zip-safe
hnph_utils.egg-info/requires.txt
hnph_utils.egg-info/top_level.txt