Metadata-Version: 2.1
Name: hnph-utils
Version: 0.0.6
Summary: 湖南品禾网络科技有限公司，Python开发工具包
Home-page: https://www.hnpinhe.cn/
Author: Yushuo
Author-email: saltfish@126.com
Maintainer: Yushuo
Maintainer-email: saltfish@126.com
License: MIT
Platform: Windows|Linux|MacOS
Requires-Python: >=3.8
